zepben/examples/__init__.py
zepben/examples/building_network_hierarchy.py
zepben/examples/connecting_to_grpc_service.py
zepben/examples/current_state_manipulations.py
zepben/examples/dsub_from_nmi.py
zepben/examples/energy_consumer_device_hierarchy.py
zepben/examples/examining_connectivity.py
zepben/examples/export_open_dss_model.py
zepben/examples/fetching_network_hierarchy.py
zepben/examples/fetching_network_model.py
zepben/examples/find_isolation_section_from_equipment.py
zepben/examples/id_csv_generator.py
zepben/examples/ieee_13_node_test_feeder.py
zepben/examples/isolation_equipment_between_nodes.py
zepben/examples/list_ewb_network_models.py
zepben/examples/network_service_interactions.py
zepben/examples/request_feeder_load_analysis_study.py
zepben/examples/request_forecast_feeder_load_analysis_study.py
zepben/examples/request_power_factory_models.py
zepben/examples/tracing.py
zepben/examples/tracing_conductor_type_by_lv_circuit.py
zepben/examples/tracing_example.py
zepben/examples/translating_to_pandapower_model.py
zepben/examples/tx_id_to_name.py
zepben/examples/utils.py
zepben/examples/studies/__init__.py
zepben/examples/studies/creating_and_uploading_study.py
zepben/examples/studies/suspect_end_of_line.py
zepben_examples-0.6.0.dist-info/licenses/LICENSE
zepben_examples-0.6.0.dist-info/METADATA
zepben_examples-0.6.0.dist-info/WHEEL
zepben_examples-0.6.0.dist-info/top_level.txt
zepben_examples-0.6.0.dist-info/RECORD
