Metadata-Version: 2.4
Name: zepben.examples
Version: 0.6.0
Summary: Module containing examples for interacting with Zepben's platform
Author-email: Zeppelin Bend <oss@zepben.com>
License-Expression: MPL-2.0
Project-URL: Repository, https://github.com/zepben/ewb-sdk-examples-python
Project-URL: Homepage, https://zepben.com
Classifier: Programming Language :: Python :: 3
Classifier: Programming Language :: Python :: 3.10
Classifier: Programming Language :: Python :: 3.11
Classifier: Programming Language :: Python :: 3.12
Classifier: Operating System :: OS Independent
Requires-Python: <3.13,>=3.10
License-File: LICENSE
Requires-Dist: zepben.eas==0.26.0
Requires-Dist: zepben.ewb==1.0.3
Requires-Dist: numba==0.60.0
Requires-Dist: geojson==2.5.0
Requires-Dist: gql[requests]==3.4.1
Requires-Dist: geopandas
Requires-Dist: pandas
Requires-Dist: shapely
Requires-Dist: tqdm
Provides-Extra: test
Requires-Dist: pytest<9,>=7.4.4; extra == "test"
Requires-Dist: pytest-cov==6.1.1; extra == "test"
Requires-Dist: pytest-asyncio==0.26.0; extra == "test"
Dynamic: license-file
